{"person1":"1da44460-3acd-46d8-b8eb-34d73fcc3f32","address":"c6a8c5bc-8c98-4570-9f68-1290b500dd61","parts":1,"recoveryDate":"10/10/2019","earningsYear":"2018","familyComposition":"Célibataire","taxBeforeCorrection":{"taxable":true,"amount":2165},"taxYear":2019,"tax":{"taxable":true,"amount":2165},"globalEarnings":18409,"taxableEarnings":18409,"referenceEarnings":18409,"dependents":1,"statementDate":"08/07/2019","partialSituation":"(*) Situation  2018  partielle","correctionError":"Ce document ne correspond pas à la situation la plus récente pour cet usager","noticeNumber":"1902099999003","taxNumber":"1902099999003"}