{"person1":"f5f3a340-711c-473d-b06e-55c441e83cd1","person2":"e88cf070-05c0-4355-9f53-336fa64b2462","address":"fe31cc1c-333d-46c6-840d-592513cc671f","parts":4,"recoveryDate":"10/10/2020","earningsYear":"2019","familyComposition":"Marié(e)s","taxBeforeCorrection":{"taxable":true,"amount":100},"taxYear":2020,"tax":{"taxable":true,"amount":100},"globalEarnings":41,"taxableEarnings":41,"referenceEarnings":39,"dependents":2,"statementDate":"08/07/2020","noticeNumber":"2001399999068","taxNumber":"2001399999068"}